Metadata-Version: 1.1
Name: json2html
Version: 1.1.0
Summary: JSON to HTML Table Representation
Home-page: https://github.com/softvar/json2html
Author: Varun Malhotra
Author-email: varun2902@gmail.com
License: MIT
Download-URL: https://github.com/softvar/json2html/tarball/1.1.0
Keywords: json,HTML,Table
Platform: UNKNOWN
Classifier: Programming Language :: Python
Classifier: Programming Language :: Python :: 2.5
Classifier: Programming Language :: Python :: 2.6
Classifier: Programming Language :: Python :: 2.7
